stringbender/__init__.py
stringbender-0.4.0.dist-info/LICENSE
stringbender-0.4.0.dist-info/METADATA
stringbender-0.4.0.dist-info/WHEEL
stringbender-0.4.0.dist-info/RECORD
