Metadata-Version: 2.1
Name: stringbender
Version: 0.4.0
Summary: A sub-class of the Python str class that adds case conversion functions.
License: FreeBSD
Author: GreaterThan, LLC
Author-email: info@greaterthan.solutions
Requires-Python: >=3.9,<4.0
Classifier: License :: Other/Proprietary License
Classifier: Programming Language :: Python :: 3
Classifier: Programming Language :: Python :: 3.9
Classifier: Programming Language :: Python :: 3.10
Classifier: Programming Language :: Python :: 3.11
Classifier: Programming Language :: Python :: 3.12
